tensorflow_model_optimization/__init__.py
tensorflow_model_optimization/python/__init__.py
tensorflow_model_optimization/python/core/__init__.py
tensorflow_model_optimization/python/core/version.py
tensorflow_model_optimization/python/core/api/__init__.py
tensorflow_model_optimization/python/core/api/clustering/__init__.py
tensorflow_model_optimization/python/core/api/clustering/keras/__init__.py
tensorflow_model_optimization/python/core/api/experimental/__init__.py
tensorflow_model_optimization/python/core/api/experimental/combine/__init__.py
tensorflow_model_optimization/python/core/api/quantization/__init__.py
tensorflow_model_optimization/python/core/api/quantization/keras/__init__.py
tensorflow_model_optimization/python/core/api/quantization/keras/collab_opts/__init__.py
tensorflow_model_optimization/python/core/api/quantization/keras/default_8bit/__init__.py
tensorflow_model_optimization/python/core/api/quantization/keras/default_8bit/default_8bit_transforms/__init__.py
tensorflow_model_optimization/python/core/api/quantization/keras/experimental/__init__.py
tensorflow_model_optimization/python/core/api/quantization/keras/experimental/default_n_bit/__init__.py
tensorflow_model_optimization/python/core/api/quantization/keras/experimental/default_n_bit/default_n_bit_transforms/__init__.py
tensorflow_model_optimization/python/core/api/quantization/keras/graph_transformations/__init__.py
tensorflow_model_optimization/python/core/api/quantization/keras/graph_transformations/model_transformer/__init__.py
tensorflow_model_optimization/python/core/api/quantization/keras/graph_transformations/transforms/__init__.py
tensorflow_model_optimization/python/core/api/quantization/keras/quantizers/__init__.py
tensorflow_model_optimization/python/core/api/sparsity/__init__.py
tensorflow_model_optimization/python/core/api/sparsity/keras/__init__.py
tensorflow_model_optimization/python/core/clustering/__init__.py
tensorflow_model_optimization-0.7.4.dist-info/METADATA
tensorflow_model_optimization-0.7.4.dist-info/WHEEL
tensorflow_model_optimization-0.7.4.dist-info/top_level.txt
tensorflow_model_optimization-0.7.4.dist-info/RECORD
